agentstack_cli/__init__.py
agentstack_cli/api.py
agentstack_cli/async_typer.py
agentstack_cli/auth_manager.py
agentstack_cli/configuration.py
agentstack_cli/console.py
agentstack_cli/utils.py
agentstack_cli/commands/__init__.py
agentstack_cli/commands/agent.py
agentstack_cli/commands/build.py
agentstack_cli/commands/mcp.py
agentstack_cli/commands/model.py
agentstack_cli/commands/self.py
agentstack_cli/commands/server.py
agentstack_cli/commands/user.py
agentstack_cli/commands/platform/__init__.py
agentstack_cli/commands/platform/base_driver.py
agentstack_cli/commands/platform/istio.py
agentstack_cli/commands/platform/lima_driver.py
agentstack_cli/commands/platform/wsl_driver.py
agentstack_cli/data/.gitignore
agentstack_cli/data/helm-chart.tgz
agentstack_cli-0.5.0.dist-info/METADATA
agentstack_cli-0.5.0.dist-info/WHEEL
agentstack_cli-0.5.0.dist-info/entry_points.txt
agentstack_cli-0.5.0.dist-info/RECORD
